wlfutil/__init__.py
wlfutil/all.py
wlfutil/all_copy.py
wlfutil-0.0.51.dist-info/LICENSE
wlfutil-0.0.51.dist-info/METADATA
wlfutil-0.0.51.dist-info/WHEEL
wlfutil-0.0.51.dist-info/top_level.txt
wlfutil-0.0.51.dist-info/RECORD
