Metadata-Version: 2.1
Name: wlfutil
Version: 0.0.51
Summary: Common utils for python.
Home-page: https://github.com/waisaa/wlf-util
Author: waisaa
Author-email: waisaa@qq.com
License: MIT Licence
Keywords: UniUtil,ConfUtil,FileUtil,DtUtil,LogUtil,InfluxUtil,MysqlUtil,ShellUtil,MinioUtil,RedisUtil
Platform: any
Requires-Python: >=3.7
Requires-Dist: colorlog (==6.6.0)
Requires-Dist: influxdb (==5.3.1)
Requires-Dist: PyMySQL (==1.0.2)
Requires-Dist: paramiko (==2.11.0)
Requires-Dist: minio (==7.1.9)
Requires-Dist: redis (==3.2.0)
